power_qt/__init__.py
power_qt/WIP/MultiListSelector.py
power_qt/WIP/StylizedExcelFile.py
power_qt/WIP/ThumbableListWidget.py
power_qt/WIP/__init__.py
power_qt/WIP/documentation_viewer.py
power_qt/WIP/dragdrop_list.py
power_qt/WIP/helper_classes.py
power_qt/buttons/__init__.py
power_qt/buttons/active_button.py
power_qt/combo_boxes/__init__.py
power_qt/combo_boxes/checkable.py
power_qt/combo_boxes/combo_boxes.py
power_qt/config_editor/__init__.py
power_qt/filter_models/__init__.py
power_qt/filter_models/base_filtering.py
power_qt/item_delegates/__init__.py
power_qt/item_delegates/basic_delegates.py
power_qt/json_editor/__init__.py
power_qt/json_editor/batch_name.py
power_qt/json_editor/data_tree.py
power_qt/json_editor/json_editor_system.py
power_qt/json_editor/json_editor_ui.py
power_qt/json_editor/ui_utils.py
power_qt/matplotlib/__init__.py
power_qt/matplotlib/qt_plotters.py
power_qt/other/__init__.py
power_qt/other/datetime_editors.py
power_qt/other/default_fields.py
power_qt/other/filebrowsers.py
power_qt/other/general_widgets.py
power_qt/other/json_models.py
power_qt/other/special_tabbars.py
power_qt/pandas_models/__init__.py
power_qt/pandas_models/basic_list_models.py
power_qt/pandas_models/basic_table_models.py
power_qt/pandas_models/filter_proxy_models.py
power_qt/tableviews/__init__.py
power_qt/tableviews/basic_tableviews.py
power_qt-0.1.2.dist-info/METADATA
power_qt-0.1.2.dist-info/WHEEL
power_qt-0.1.2.dist-info/top_level.txt
power_qt-0.1.2.dist-info/RECORD
