Metadata-Version: 2.4
Name: Power_Qt
Version: 0.1.2
Summary: A python library for generalized Qt models for PyQt6
Home-page: https://github.com/Squidu/Power_Qt
Author: Dominick Gagliano
Author-email: dgaglian96@gmail.com
Classifier: Development Status :: 4 - Beta
Classifier: Intended Audience :: Developers
Classifier: License :: OSI Approved :: MIT License
Classifier: Natural Language :: English
Classifier: Operating System :: Microsoft :: Windows
Classifier: Programming Language :: Python :: 3.10
Classifier: Programming Language :: Python :: 3.11
Classifier: Programming Language :: Python :: 3.12
Requires-Python: >=3.10,<3.13
Requires-Dist: superqt>=0.7.6
Requires-Dist: pandas~=2.3.2
Requires-Dist: numpy~=2.3.2
Requires-Dist: sympy~=1.14.0
Requires-Dist: polars~=1.33.1
Requires-Dist: Pint~=0.25
Requires-Dist: matplotlib~=3.10.6
Requires-Dist: setuptools~=80.9.0
Dynamic: author
Dynamic: author-email
Dynamic: classifier
Dynamic: description
Dynamic: description-content-type
Dynamic: home-page
Dynamic: requires-dist
Dynamic: requires-python
Dynamic: summary
